Metadata-Version: 1.0
Name: edssdka
Version: 0.0.6
Summary: eds sdk
Home-page: http://test.me
Author: testa
Author-email: testa@gmail.com
License: MIT Licence
Keywords: pip,datacanvas,eds,xiaoh
Platform: any
